appboot/.DS_Store
appboot/__init__.py
appboot/__main__.py
appboot/_compat.py
appboot/apps.py
appboot/asgi.py
appboot/base.py
appboot/commands.py
appboot/conf/.DS_Store
appboot/conf/__init__.py
appboot/conf/app_template/.DS_Store
appboot/conf/app_template/__init__.py.j2
appboot/conf/app_template/apps.py.j2
appboot/conf/app_template/models.py.j2
appboot/conf/app_template/schema.py.j2
appboot/conf/app_template/tests.py
appboot/conf/app_template/views.py.j2
appboot/conf/default.py
appboot/conf/project_template/manage.py.j2
appboot/conf/project_template/project_name/__init__.py.j2
appboot/conf/project_template/project_name/asgi.py.j2
appboot/conf/project_template/project_name/settings.py.j2
appboot/conf/project_template/project_name/urls.py.j2
appboot/conf/pydantic_settings.py
appboot/db.py
appboot/exceptions.py
appboot/filters.py
appboot/models.py
appboot/pagination.py
appboot/params.py
appboot/py.typed
appboot/repository.py
appboot/response.py
appboot/schema.py
appboot/timezone.py
appboot/utils.py
appboot-0.3.5.dist-info/LICENSE
appboot-0.3.5.dist-info/METADATA
appboot-0.3.5.dist-info/WHEEL
appboot-0.3.5.dist-info/entry_points.txt
appboot-0.3.5.dist-info/RECORD
