Metadata-Version: 2.1
Name: appboot
Version: 0.3.5
Summary: Use FastAPI like Django
Home-page: https://github.com/taogeYT/appboot
Author: liyatao
Author-email: liyatao001@gmail.com
Requires-Python: >=3.9,<4.0
Classifier: Programming Language :: Python :: 3
Classifier: Programming Language :: Python :: 3.9
Classifier: Programming Language :: Python :: 3.10
Classifier: Programming Language :: Python :: 3.11
Classifier: Programming Language :: Python :: 3.12
Provides-Extra: pydantic-settings
Requires-Dist: fastapi (>=0.95.0)
Requires-Dist: jinja2 (>=2.11.2)
Requires-Dist: pydantic (>=1.10.6)
Requires-Dist: pydantic-settings (>=2.0.0,<3.0.0) ; extra == "pydantic-settings"
Requires-Dist: python-dotenv (>=0.10.4)
Requires-Dist: sqlalchemy[asyncio] (>=2.0.0,<3.0.0)
Requires-Dist: typer (>=0.8.0)
Requires-Dist: typing_extensions (>=4.2.0)
Requires-Dist: uvicorn[standard] (>=0.17.0)
Project-URL: Repository, https://github.com/taogeYT/appboot
